ammonkey/__init__.py
ammonkey/__main__.py
ammonkey/ammonkey_example.py
ammonkey/monkeyUnityv1_8.py
ammonkey/cfgs/amm-config.yaml
ammonkey/cfgs/calibration.toml
ammonkey/cfgs/config_arm.toml
ammonkey/cfgs/config_hand.toml
ammonkey/core/__init__.py
ammonkey/core/ani.py
ammonkey/core/camConfig.py
ammonkey/core/config.py
ammonkey/core/daet.py
ammonkey/core/dlc.py
ammonkey/core/dlcCollector.py
ammonkey/core/expNote.py
ammonkey/core/experiment.py
ammonkey/core/fileOp.py
ammonkey/core/finalize.py
ammonkey/core/mdlSet.py
ammonkey/core/status.py
ammonkey/core/statusChecker.py
ammonkey/core/sync.py
ammonkey/dask/__init__.py
ammonkey/dask/dask_executors.py
ammonkey/dask/dask_factory.py
ammonkey/dask/dask_scheduler.py
ammonkey/dask/dask_task.py
ammonkey/dask/dask_util.py
ammonkey/dask/start_dask.py
ammonkey/gui_v3/__init__.py
ammonkey/gui_v3/ambmky.ico
ammonkey/gui_v3/flet_main.py
ammonkey/gui_v3/landfill.py
ammonkey/gui_v3/business/full_pipeline.py
ammonkey/gui_v3/components/__init__.py
ammonkey/gui_v3/components/cam_config.py
ammonkey/gui_v3/components/file_tree.py
ammonkey/gui_v3/components/file_trees_tab.py
ammonkey/gui_v3/components/flet_logging.py
ammonkey/gui_v3/components/note_selector.py
ammonkey/gui_v3/tabs/__init__.py
ammonkey/gui_v3/tabs/tab_ani.py
ammonkey/gui_v3/tabs/tab_dlc.py
ammonkey/gui_v3/tabs/tab_final.py
ammonkey/gui_v3/tabs/tab_setting.py
ammonkey/gui_v3/tabs/tab_setup.py
ammonkey/gui_v3/tabs/tab_sync.py
ammonkey/scripts/batch_ani.py
ammonkey/scripts/batch_dlc.py
ammonkey/scripts/batch_sync.py
ammonkey/scripts/get_all_tasks.py
ammonkey/utils/PathManager.py
ammonkey/utils/ROIConfig.py
ammonkey/utils/SyncAll.py
ammonkey/utils/VidSyncAud.py
ammonkey/utils/VidSyncLED.py
ammonkey/utils/__init__.py
ammonkey/utils/copyUSB.py
ammonkey/utils/eventMarker.py
ammonkey/utils/isCSVIdentical.py
ammonkey/utils/log.py
ammonkey/utils/ol_logging.py
ammonkey/utils/pullAniAll - Copy.py
ammonkey/utils/pullAniAll.py
ammonkey/utils/pullDLCAll.py
ammonkey/utils/quickSyncOnly.py
ammonkey-3.3.2.dist-info/licenses/LICENSE
ammonkey-3.3.2.dist-info/METADATA
ammonkey-3.3.2.dist-info/WHEEL
ammonkey-3.3.2.dist-info/entry_points.txt
ammonkey-3.3.2.dist-info/top_level.txt
ammonkey-3.3.2.dist-info/RECORD
