Metadata-Version: 2.4
Name: ammonkey
Version: 3.3.2
Summary: A package for organizing, processing and performing markerless 3D tracking on primate behavior videos using DeepLabCut, Anipose, with a user-friendly GUI.
Author-email: Mel Xu <penkonno@gmail.com>
License: MIT License
Project-URL: Homepage, https://github.com/melokeo/AmbiguousMonkey
Project-URL: Bug Tracker, https://github.com/melokeo/AmbiguousMonkey/issues
Project-URL: Documentation, https://github.com/Melokeo/AmbiguousMonkey/blob/main/README.md
Keywords: neuroscience,computer vision,behavior analysis,deeplabcut,anipose
Classifier: Development Status :: 4 - Beta
Classifier: Programming Language :: Python :: 3
Classifier: Programming Language :: Python :: 3.10
Classifier: License :: OSI Approved :: MIT License
Classifier: Operating System :: OS Independent
Classifier: Operating System :: Microsoft :: Windows
Classifier: Topic :: Scientific/Engineering
Classifier: Intended Audience :: Science/Research
Requires-Python: ~=3.10
License-File: LICENSE
Requires-Dist: pandas
Requires-Dist: numpy
Requires-Dist: scipy
Requires-Dist: matplotlib
Requires-Dist: diskcache
Requires-Dist: tqdm
Requires-Dist: pyyaml
Requires-Dist: librosa
Requires-Dist: openpyxl
Requires-Dist: pywin32~=310.0; sys_platform == "win32"
Requires-Dist: opencv-python==4.11.0.86
Provides-Extra: gui
Requires-Dist: flet~=0.28.3; extra == "gui"
Provides-Extra: da
Requires-Dist: deeplabcut==3.0.0rc7; extra == "da"
Requires-Dist: tensorflow==2.10.*; extra == "da"
Requires-Dist: tensorpack; extra == "da"
Requires-Dist: tf-slim; extra == "da"
Requires-Dist: qtpy; extra == "da"
Requires-Dist: torch==2.0.1; extra == "da"
Requires-Dist: torchvision==0.15.2; extra == "da"
Requires-Dist: torchaudio==2.0.2; extra == "da"
Requires-Dist: qdarkstyle; extra == "da"
Requires-Dist: napari; extra == "da"
Requires-Dist: napari_deeplabcut; extra == "da"
Requires-Dist: anipose; extra == "da"
Provides-Extra: dev
Requires-Dist: pytest; extra == "dev"
Requires-Dist: black; extra == "dev"
Requires-Dist: twine; extra == "dev"
Requires-Dist: build; extra == "dev"
Provides-Extra: all
Requires-Dist: ammonkey[cv,dev,gui]; extra == "all"
Dynamic: license-file
